pnnplus/__init__.py
pnnplus/pnnplus.py
pnnplus-0.1.8.dist-info/LICENSE
pnnplus-0.1.8.dist-info/METADATA
pnnplus-0.1.8.dist-info/WHEEL
pnnplus-0.1.8.dist-info/top_level.txt
pnnplus-0.1.8.dist-info/RECORD
