Metadata-Version: 2.1
Name: pnnplus
Version: 0.1.8
Summary: A Python library that implements Parametric Neural Networks (PNN) for use in high-energy physics and beyond.
Home-page: https://github.com/feixukeji/pnnplus
Author: Xulei Sun
Author-email: sxl66@outlook.com
License: GPL-3.0
Classifier: Programming Language :: Python :: 3
Classifier: License :: OSI Approved :: GNU General Public License v3 (GPLv3)
Classifier: Operating System :: OS Independent
Requires-Python: >=3.6
License-File: LICENSE
Requires-Dist: numpy
Requires-Dist: pandas
Requires-Dist: seaborn
Requires-Dist: tensorflow
Requires-Dist: scikit-learn
Requires-Dist: joblib
Requires-Dist: matplotlib
Requires-Dist: IPython
Provides-Extra: hep
Requires-Dist: uproot; extra == "hep"
Requires-Dist: awkward; extra == "hep"
